potypo/__init__.py
potypo/__main__.py
potypo/check.py
potypo/chunkers.py
potypo/filters.py
potypo-0.0.2.dist-info/DESCRIPTION.rst
potypo-0.0.2.dist-info/METADATA
potypo-0.0.2.dist-info/RECORD
potypo-0.0.2.dist-info/WHEEL
potypo-0.0.2.dist-info/entry_points.txt
potypo-0.0.2.dist-info/metadata.json
potypo-0.0.2.dist-info/top_level.txt
