Metadata-Version: 1.1
Name: potypo
Version: 0.0.2
Summary: spellchecking for .po-files
Home-page: https://github.com/koebi/potypo
Author: Jakob Schnell
Author-email: potypo@ezelo.de
License: UNKNOWN
Keywords: setuptools development spellcheck translation typo gettext
Platform: UNKNOWN
Classifier: Development Status :: 3 - Alpha
Classifier: Intended Audience :: Developers
Classifier: Topic :: Software Development :: Build Tools
Classifier: License :: OSI Approved :: MIT License
Classifier: Programming Language :: Python :: 3
Classifier: Programming Language :: Python :: 3.4
Classifier: Programming Language :: Python :: 3.5
Classifier: Programming Language :: Python :: 3.6
